aiostun/__init__.py
aiostun/attribute.py
aiostun/client.py
aiostun/constants.py
aiostun/nat.py
aiostun/stun.py
aiostun-0.6.1.dist-info/licenses/LICENSE
tests/__init__.py
tests/test_codec.py
aiostun-0.6.1.dist-info/METADATA
aiostun-0.6.1.dist-info/WHEEL
aiostun-0.6.1.dist-info/top_level.txt
aiostun-0.6.1.dist-info/RECORD
