Metadata-Version: 2.4
Name: aiostun
Version: 0.6.1
Summary: Asynchronous STUN client for Python with UDP, TCP and TLS support
Home-page: https://github.com/dmachard/python-aiostun
Author: Denis MACHARD
Author-email: d.machard@gmail.com
Keywords: stun client
Platform: any
Classifier: License :: OSI Approved :: MIT License
Classifier: Programming Language :: Python :: 3
Classifier: Operating System :: OS Independent
Classifier: Topic :: Software Development :: Libraries
License-File: LICENSE
Dynamic: author
Dynamic: author-email
Dynamic: classifier
Dynamic: description
Dynamic: description-content-type
Dynamic: home-page
Dynamic: keywords
Dynamic: license-file
Dynamic: platform
Dynamic: summary
